aws_recommendation_a18/__init__.py
aws_recommendation_a18/cloudwatch.py
aws_recommendation_a18/cost_estimations.py
aws_recommendation_a18/dynamodb.py
aws_recommendation_a18/ebs.py
aws_recommendation_a18/ec2.py
aws_recommendation_a18/elb.py
aws_recommendation_a18/kms.py
aws_recommendation_a18/rds.py
aws_recommendation_a18/recommendation.py
aws_recommendation_a18/redshift.py
aws_recommendation_a18/s3.py
aws_recommendation_a18/truted_advisor.py
aws_recommendation_a18/utils.py
aws_recommendation_a18-0.1.8.dist-info/LICENCE
aws_recommendation_a18-0.1.8.dist-info/METADATA
aws_recommendation_a18-0.1.8.dist-info/WHEEL
aws_recommendation_a18-0.1.8.dist-info/top_level.txt
aws_recommendation_a18-0.1.8.dist-info/RECORD
